cryptortool/__init__.py
cryptortool/cli.py
cryptortool/cryptortool.py
cryptortool/hash.py
Cryptortool-1.5.6.dist-info/LICENSE
Cryptortool-1.5.6.dist-info/METADATA
Cryptortool-1.5.6.dist-info/WHEEL
Cryptortool-1.5.6.dist-info/entry_points.txt
Cryptortool-1.5.6.dist-info/top_level.txt
Cryptortool-1.5.6.dist-info/RECORD
